LICENSE.txt
pytorch_polkadots/__init__.py
pytorch_polkadots/datasets.py
pytorch_polkadots-0.1.1.dist-info/LICENSE.txt
pytorch_polkadots-0.1.1.dist-info/WHEEL
pytorch_polkadots-0.1.1.dist-info/METADATA
pytorch_polkadots-0.1.1.dist-info/RECORD
