Metadata-Version: 2.1
Name: pytorch-polkadots
Version: 0.1.1
Summary: Provides the ability to construct a simulated image dataset on the fly with different characteristics.
Home-page: https://github.com/fac2003/pytorch_polkadots
License: MIT
Keywords: machine learning,simulated datasets,images
Author: Fabien  Campagne
Author-email: fac2003@gmail.com
Requires-Python: >=3.7,<4.0
Classifier: Development Status :: 4 - Beta
Classifier: Intended Audience :: Developers
Classifier: License :: OSI Approved :: MIT License
Classifier: Operating System :: OS Independent
Classifier: Programming Language :: Python :: 3
Classifier: Programming Language :: Python :: 3.7
Classifier: Programming Language :: Python :: 3.8
Classifier: Programming Language :: Python :: 3.9
Classifier: Topic :: Scientific/Engineering
Classifier: Topic :: Scientific/Engineering :: Artificial Intelligence
Requires-Dist: Pillow (>=8.1.2,<9.0.0)
Requires-Dist: torch (>=1.8.1,<2.0.0)
Project-URL: Repository, https://github.com/fac2003/pytorch_polkadots
